suzieq/__init__.py
suzieq/cli/__init__.py
suzieq/cli/nubia_patch.py
suzieq/cli/sq_cli.py
suzieq/cli/sq_nubia_context.py
suzieq/cli/sq_nubia_plugin.py
suzieq/cli/sq_nubia_statusbar.py
suzieq/cli/sqcmds/AddressCmd.py
suzieq/cli/sqcmds/ArpndCmd.py
suzieq/cli/sqcmds/BgpCmd.py
suzieq/cli/sqcmds/DevconfigCmd.py
suzieq/cli/sqcmds/DeviceCmd.py
suzieq/cli/sqcmds/EvpnVniCmd.py
suzieq/cli/sqcmds/FsCmd.py
suzieq/cli/sqcmds/InterfaceCmd.py
suzieq/cli/sqcmds/InventoryCmd.py
suzieq/cli/sqcmds/LldpCmd.py
suzieq/cli/sqcmds/MacCmd.py
suzieq/cli/sqcmds/MlagCmd.py
suzieq/cli/sqcmds/NamespaceCmd.py
suzieq/cli/sqcmds/NetworkCmd.py
suzieq/cli/sqcmds/OspfCmd.py
suzieq/cli/sqcmds/PathCmd.py
suzieq/cli/sqcmds/RouteCmd.py
suzieq/cli/sqcmds/SqPollerCmd.py
suzieq/cli/sqcmds/TableCmd.py
suzieq/cli/sqcmds/TopcpuCmd.py
suzieq/cli/sqcmds/TopmemCmd.py
suzieq/cli/sqcmds/TopologyCmd.py
suzieq/cli/sqcmds/VlanCmd.py
suzieq/cli/sqcmds/__init__.py
suzieq/cli/sqcmds/command.py
suzieq/cli/sqcmds/context_commands.py
suzieq/config/arpnd.yml
suzieq/config/bgp.yml
suzieq/config/devconfig.yml
suzieq/config/device.yml
suzieq/config/etc/cert.pem
suzieq/config/etc/inventory/inventory.yaml
suzieq/config/etc/key.pem
suzieq/config/etc/ssh_insecure_key
suzieq/config/etc/suzieq-cfg.yml
suzieq/config/evpnVni.yml
suzieq/config/fs.yml
suzieq/config/ifCounters.yml
suzieq/config/interfaces.yml
suzieq/config/inventory.yml
suzieq/config/lldp.yml
suzieq/config/macs.yml
suzieq/config/mlag.yml
suzieq/config/ospfIf.yml
suzieq/config/ospfNbr.yml
suzieq/config/routes.yml
suzieq/config/schema/address.avsc
suzieq/config/schema/arpnd.avsc
suzieq/config/schema/bgp.avsc
suzieq/config/schema/devconfig.avsc
suzieq/config/schema/device.avsc
suzieq/config/schema/evpnVni.avsc
suzieq/config/schema/fs.avsc
suzieq/config/schema/ifCounters.avsc
suzieq/config/schema/interfaces.avsc
suzieq/config/schema/inventory.avsc
suzieq/config/schema/lldp.avsc
suzieq/config/schema/macs.avsc
suzieq/config/schema/mlag.avsc
suzieq/config/schema/namespace.avsc
suzieq-0.24.0.dist-info/AUTHORS.md
suzieq-0.24.0.dist-info/LICENSE
suzieq-0.24.0.dist-info/METADATA
suzieq-0.24.0.dist-info/WHEEL
suzieq-0.24.0.dist-info/entry_points.txt
suzieq-0.24.0.dist-info/RECORD
