Metadata-Version: 2.1
Name: suzieq
Version: 0.24.0
Summary: A framework and application for network observability
Home-page: https://www.stardustsystems.net/suzieq/
License: Apache-2.0
Keywords: network,Cisco,Arista,Junos,observability,Cumulus,monitoring,SoNIC,IOS
Author: suzieq dev team
Maintainer: suzieq dev team
Requires-Python: >3.8.1,<3.10
Classifier: License :: OSI Approved :: Apache Software License
Classifier: Programming Language :: Python :: 3
Classifier: Programming Language :: Python :: 3.9
Classifier: Topic :: System :: Networking :: Monitoring
Requires-Dist: PyYAML
Requires-Dist: aiofiles
Requires-Dist: aiohttp (>3.8,<4.0)
Requires-Dist: altair (>3.2,<5.0)
Requires-Dist: async-timeout (>4.0,<5.0)
Requires-Dist: asyncssh (>=2.14,<2.15)
Requires-Dist: ciscoconfparse (>=1.6.21,<1.7.0)
Requires-Dist: colorama (>=0.4.4,<0.5.0)
Requires-Dist: dateparser (>=1.1,<1.2)
Requires-Dist: faker (>=4.18,<4.19)
Requires-Dist: fastapi (>=0.95.2,<0.96.0)
Requires-Dist: graphviz (>=0.15,<0.16)
Requires-Dist: jellyfish (>=0.10,<0.11)
Requires-Dist: jsonpath-ng (>=1.6,<1.7)
Requires-Dist: matplotlib (>=3.7,<3.8)
Requires-Dist: natsort (>=8.0.0,<9.0.0)
Requires-Dist: netconan (>=0.11.2,<0.12.0)
Requires-Dist: networkx (>=2.4,<2.5)
Requires-Dist: notebook (==6.4.12)
Requires-Dist: numpy (>=1.20,<1.21)
Requires-Dist: packaging (>=21.3,<21.4)
Requires-Dist: pandas (>=1.5,<1.6)
Requires-Dist: prompt-toolkit (>2)
Requires-Dist: psutil (>=5.9.4,<5.10.0)
Requires-Dist: pyarrow (>=11.0,<11.1)
Requires-Dist: pydantic (<2.0)
Requires-Dist: pyparsing (>=2.2.0,<3.0)
Requires-Dist: python-nubia (==0.2b5)
Requires-Dist: pyvmomi (>=8.0.2.0.1,<9.0.0.0.0)
Requires-Dist: streamlit (==1.11.1)
Requires-Dist: streamlit-aggrid (>=0.2.2,<0.3.0)
Requires-Dist: tabulate (>=0.8.7,<0.9.0)
Requires-Dist: textfsm
Requires-Dist: tzlocal (<3.0)
Requires-Dist: urllib3 (>=1.26.12,<1.27.0)
Requires-Dist: uvicorn (>=0.15.0,<0.16.0)
Requires-Dist: uvloop
Requires-Dist: xmltodict (>=0.12.0,<0.13.0)
Project-URL: Documentation, https://suzieq.readthedocs.io
Project-URL: Repository, https://github.com/netenglabs/suzieq
